sitealias/__init__.py
sitealias/admin.py
sitealias/apps.py
sitealias/middleware.py
sitealias/mixins.py
sitealias/models.py
sitealias/shortcuts.py
sitealias/tests.py
sitealias/views.py
sitealias/migrations/0001_initial.py
sitealias/migrations/0002_auto_20210203_1648.py
sitealias/migrations/0003_auto_20210920_1319.py
sitealias/migrations/__init__.py
django_site_aliases-0.1.2.dist-info/METADATA
django_site_aliases-0.1.2.dist-info/WHEEL
django_site_aliases-0.1.2.dist-info/top_level.txt
django_site_aliases-0.1.2.dist-info/RECORD
