Metadata-Version: 2.1
Name: django-site-aliases
Version: 0.1.2
Summary: A tool to support site aliases that wrap around Django's Site framework
Home-page: https://github.com/renderbox/django-site-aliases/
Author: Grant Viklund
Author-email: renderbox@gmail.com
License: MIT license
Keywords: django,app
Platform: UNKNOWN
Classifier: Development Status :: 2 - Pre-Alpha
Classifier: Intended Audience :: Developers
Classifier: Programming Language :: Python :: 3 :: Only
Classifier: Programming Language :: Python :: 3.6
Classifier: Programming Language :: Python :: 3.7
Requires-Python: >=3.6
Requires-Dist: Django (<4.1,>=3.0)
Requires-Dist: dj-database-url
Requires-Dist: django-crispy-forms
Provides-Extra: build
Requires-Dist: setuptools ; extra == 'build'
Requires-Dist: wheel ; extra == 'build'
Requires-Dist: twine ; extra == 'build'
Requires-Dist: m2r ; extra == 'build'
Provides-Extra: dev
Requires-Dist: django-allauth ; extra == 'dev'
Provides-Extra: docs
Requires-Dist: m2r ; extra == 'docs'
Requires-Dist: coverage ; extra == 'docs'
Requires-Dist: Sphinx ; extra == 'docs'
Requires-Dist: sphinx-bootstrap-theme ; extra == 'docs'
Requires-Dist: sphinx-rtd-theme ; extra == 'docs'
Requires-Dist: sphinx-js ; extra == 'docs'
Requires-Dist: sphinx-autobuild ; extra == 'docs'
Provides-Extra: prod
Provides-Extra: test
